tfkit/__init__.py
tfkit/dump.py
tfkit/eval.py
tfkit/train.py
tfkit/task/__init__.py
tfkit/task/clas/__init__.py
tfkit/task/clas/model.py
tfkit/task/clas/preprocessor.py
tfkit/task/clm/__init__.py
tfkit/task/clm/model.py
tfkit/task/clm/preprocessor.py
tfkit/task/once/__init__.py
tfkit/task/once/model.py
tfkit/task/once/preprocessor.py
tfkit/task/oncectc/__init__.py
tfkit/task/oncectc/model.py
tfkit/task/qa/__init__.py
tfkit/task/qa/model.py
tfkit/task/qa/preprocessor.py
tfkit/task/seq2seq/__init__.py
tfkit/task/seq2seq/model.py
tfkit/task/seq2seq/preprocessor.py
tfkit/task/tag/__init__.py
tfkit/task/tag/model.py
tfkit/task/tag/preprocessor.py
tfkit/test/__init__.py
tfkit/test/test_atrain.py
tfkit/test/test_package.py
tfkit/test/test_zeval.py
tfkit/test/test_zzdump.py
tfkit/utility/__init__.py
tfkit/utility/data_filereader.py
tfkit/utility/data_loader.py
tfkit/utility/data_processor.py
tfkit/utility/datafile.py
tfkit/utility/dataloader.py
tfkit/utility/dataset.py
tfkit/utility/eval_metric.py
tfkit/utility/logger.py
tfkit/utility/loss.py
tfkit/utility/model.py
tfkit/utility/predictor.py
tfkit/utility/preprocess.py
tfkit/utility/tok.py
tfkit-0.8.20.dist-info/LICENSE
tfkit-0.8.20.dist-info/METADATA
tfkit-0.8.20.dist-info/WHEEL
tfkit-0.8.20.dist-info/entry_points.txt
tfkit-0.8.20.dist-info/top_level.txt
tfkit-0.8.20.dist-info/RECORD
