Metadata-Version: 2.1
Name: tfkit
Version: 0.8.20
Summary: Transformers kit - Multi-task QA/Tagging/Multi-label Multi-Class Classification/Generation with BERT/ALBERT/T5/BERT
Home-page: https://github.com/voidful/TFkit
Author: Voidful
Author-email: voidful.stack@gmail.com
License: Apache
Keywords: transformer huggingface nlp multi-task multi-class multi-label classification generation tagging deep learning machine reading
Platform: UNKNOWN
Classifier: Development Status :: 4 - Beta
Classifier: Intended Audience :: Science/Research
Classifier: Topic :: Scientific/Engineering :: Artificial Intelligence
Classifier: License :: OSI Approved :: Apache Software License
Classifier: Programming Language :: Python :: 3.6
Requires-Python: >=3.5.0
License-File: LICENSE
Requires-Dist: transformers (>=3.3.0)
Requires-Dist: tensorboard
Requires-Dist: tensorboardX
Requires-Dist: torch
Requires-Dist: matplotlib
Requires-Dist: nlp2 (>=1.8.44)
Requires-Dist: tqdm (>=4.45.0)
Requires-Dist: inquirer
Requires-Dist: numpy
Requires-Dist: scipy (>=1.10.1)
Requires-Dist: pytorch-crf
Requires-Dist: sentencepiece
Requires-Dist: pandas
Requires-Dist: accelerate (>=0.5.1)
Requires-Dist: joblib
Requires-Dist: scikit-learn
Requires-Dist: editdistance
